whisperkey/.flake8
whisperkey/.gitignore
whisperkey/__init__.py
whisperkey/config.py
whisperkey/file_handler.py
whisperkey/keyboard_handler.py
whisperkey/main.py
whisperkey/utils.py
whisperkey-0.2.0.dist-info/METADATA
whisperkey-0.2.0.dist-info/WHEEL
whisperkey-0.2.0.dist-info/entry_points.txt
whisperkey-0.2.0.dist-info/RECORD
