Metadata-Version: 2.3
Name: whisperkey
Version: 0.2.0
Summary: Whisper key
License: MIT
Author: Daniel
Author-email: danielratmiroff@pm.me
Requires-Python: >=3.12,<4.0
Classifier: License :: OSI Approved :: MIT License
Classifier: Programming Language :: Python :: 3
Classifier: Programming Language :: Python :: 3.12
Classifier: Programming Language :: Python :: 3.13
Requires-Dist: appdirs (>=1.4.4,<2.0.0)
Requires-Dist: dbus-python (>=1.3.2,<2.0.0)
Requires-Dist: notify2 (>=0.3.1,<0.4.0)
Requires-Dist: openai (>=1.66.2,<2.0.0)
Requires-Dist: psutil (>=7.0.0,<8.0.0)
Requires-Dist: pyaudio (>=0.2.14,<0.3.0)
Requires-Dist: pydantic (>=2.10.6,<3.0.0)
Requires-Dist: pynput (==1.7.8)
Requires-Dist: pyperclip (>=1.9.0,<2.0.0)
Project-URL: documentation, https://github.com/Danielratmiroff/whisper-key#readme
Project-URL: homepage, https://github.com/Danielratmiroff/whisper-key
Project-URL: issues, https://github.com/Danielratmiroff/whisper-key/issues
Project-URL: repository, https://github.com/Danielratmiroff/whisper-key
